mindbot/__init__.py
mindbot/ai_functions.py
pymindbot-0.1.dist-info/LICENSE
pymindbot-0.1.dist-info/METADATA
pymindbot-0.1.dist-info/WHEEL
pymindbot-0.1.dist-info/top_level.txt
pymindbot-0.1.dist-info/RECORD
