Metadata-Version: 2.1
Name: pymindbot
Version: 0.1
Summary: PyMindBot: MindBot Ai Library Large Language Model.
Home-page: https://github.com/yourusername/pymindbot
Author: Ahmed Helmy Ali Eletr
Author-email: ahmedhelmyali.dev@gmail.com
Classifier: Programming Language :: Python :: 3
Classifier: License :: OSI Approved :: MIT License
Classifier: Operating System :: OS Independent
Requires-Python: >=3.6
License-File: LICENSE
Requires-Dist: google-generativeai
Requires-Dist: httpx
Requires-Dist: pytesseract
Requires-Dist: Pillow
